LICENSE
MANIFEST.in
README.md
requirements.txt
setup.py
pyauto/__init__.py
pyauto.salt_serial.egg-info/PKG-INFO
pyauto.salt_serial.egg-info/SOURCES.txt
pyauto.salt_serial.egg-info/dependency_links.txt
pyauto.salt_serial.egg-info/requires.txt
pyauto.salt_serial.egg-info/top_level.txt
pyauto/salt_serial/__init__.py
pyauto/salt_serial/commands.py
pyauto/salt_serial/config.py