Metadata-Version: 1.0
Name: pyauto.salt-serial
Version: 0.0.1
Summary: A module that serializes a Salt states tree or pillar into a base-64 encoded blob.
Home-page: https://github.com/adamjaso/pyauto/tree/master/openvpn
Author: Adam Jaso
Author-email: UNKNOWN
License: GNU General Public License V2
Platform: UNKNOWN
